<tei xml:space="preserve">
    <teiHeader>
        <fileDesc xml:id="_0"/>
    </teiHeader>
    <text xml:lang="en">
        <listBibl>

        Rs.103.53 + Rs.103.53<lb/> Rs.157.78 + Rs.155.27<lb/> Rs.208.09 + Rs.207.07<lb/> 
        <bibl>Rs.82.44 + Rs.82.82<lb/> </bibl>

        Rs.646.44 + Rs.641.93<lb/> Rs.552.12 + Rs.548.73<lb/> Rs.322.69 + Rs.320.95<lb/> Rs.264.47 + Rs.264.01<lb/> 
        <bibl>Rs.207.06<lb/> </bibl>
<bibl>Rs.313.05<lb/> </bibl>
<bibl>Rs.415.16<lb/> </bibl>
<bibl>Rs.165.26<lb/> </bibl>
<bibl>Rs.1288.37<lb/> </bibl>
<bibl>Rs.1100.85<lb/> </bibl>
<bibl>Rs.643.64<lb/> </bibl>
<bibl>Rs.528.48<lb/> </bibl>
<bibl>Proceedings No.1/2(4)/2014-LS-II, dated 04.03.2014:-<lb/>Category<lb/> Basic Wages + VDA<lb/> </bibl>
Total<lb/> 1. Excavation &amp; removal of over<lb/> burden with 50 meters Lead/ 1.5<lb/> meters lift. *<lb/> (i) Soft Soil<lb/> (ii) Soft Soil with rock<lb/> (iii) Rock<lb/> 2. Removal and stacking of<lb/> rejected stones with 50 meters<lb/> lead/1.5 Meters lift. *<lb/> 3. Stone breaking or Stone<lb/> Crushing for the Stone size of:-<lb/>1.0 inch to 1.5 inches<lb/> Above 1.5 inches to 3.0 inches<lb/> Above 3.0 inches to 5.0 inches<lb/> Above 5.0 inches<lb/> 
        <bibl>Rs.103.53 + Rs.115.87<lb/> </bibl>
<bibl>Rs.157.78 + Rs.173.78<lb/> </bibl>
<bibl>Rs.208.09 + Rs.231.76<lb/> </bibl>
<bibl>Rs.82.44 + Rs.92.69<lb/> </bibl>
<bibl>Rs.646.44 + Rs.718.47<lb/> </bibl>
<bibl>Rs.552.12 + Rs.614.16<lb/> </bibl>
<bibl>Rs.322.69 + Rs.359.22<lb/> </bibl>
<bibl>Rs.264.47 + Rs.295.49<lb/> </bibl>
<bibl>Rs.219.40<lb/> </bibl>
<bibl>Rs.331.56<lb/> </bibl>
<bibl>Rs.439.85<lb/> </bibl>
<bibl>Rs.175.13<lb/> </bibl>
<bibl>Rs.1364.91<lb/> </bibl>
<bibl>Rs.1166.28<lb/> </bibl>
<bibl>Rs.681.91<lb/> </bibl>
<bibl>Rs.559.96<lb/> </bibl>
<bibl>Proceedings No.1/17(4)/2014-LS-II, dated 29.09.2014:-<lb/></bibl>

        Category<lb/> Basic Wages + VDA<lb/> Total<lb/> 1. Excavation &amp; removal of over<lb/> burden with 50 meters Lead/ 1.5<lb/> meters lift. *<lb/> (i) Soft Soil<lb/> (ii) Soft Soil with rock<lb/> (iii) Rock<lb/> 2. Removal and stacking of<lb/> rejected stones with 50 meters<lb/> lead/1.5 Meters lift. *<lb/> 
        <bibl>Rs.103.53 + Rs.117.87<lb/> </bibl>
<bibl>Rs.157.78 + Rs.176.79<lb/> </bibl>
<bibl>Rs.208.09 + Rs.235.77<lb/> </bibl>
<bibl>Rs.82.44 + Rs.94.29<lb/> </bibl>
<bibl>Rs.221.40<lb/> </bibl>
<bibl>Rs.334.57<lb/> </bibl>
<bibl>Rs.443.80<lb/> </bibl>
<bibl>Rs.176.73<lb/> </bibl>

        96<lb/> Category<lb/> Basic Wages + VDA<lb/> Total<lb/> 3. Stone breaking or Stone<lb/> Crushing for the Stone size of:-<lb/>1.0 inch to 1.5 inches<lb/> Above 1.5 inches to 3.0 inches<lb/> Above 3.0 inches to 5.0 inches<lb/> Above 5.0 inches<lb/> 
        <bibl>Rs.646.44 + Rs.730.91<lb/> </bibl>
<bibl>Rs.552.12 + Rs.624.80<lb/> </bibl>
<bibl>Rs.322.69 + Rs.365.44<lb/> </bibl>
<bibl>Rs.264.47 + Rs.300.61<lb/> </bibl>
<bibl>Rs.1377.35<lb/> </bibl>
<bibl>Rs.1176.92<lb/> </bibl>
<bibl>Rs.688.13<lb/> </bibl>
<bibl>Rs.565.08<lb/> </bibl>
<bibl>Proceedings No.1/3(4)/2015-LS-II, dated 30.03.2015:-<lb/>Category<lb/> Basic Wages + VDA<lb/> </bibl>
Total<lb/> 1. Excavation &amp; removal of over<lb/> burden with 50 meters Lead/ 1.5<lb/> meters lift. *<lb/> (i) Soft Soil<lb/> (ii) Soft Soil with rock<lb/> (iii) Rock<lb/> 2. Removal and stacking of<lb/> rejected stones with 50 meters<lb/> lead/1.5 Meters lift. *<lb/> 3. Stone breaking or Stone<lb/> Crushing for the Stone size of:-<lb/>1.0 inch to 1.5 inches<lb/> Above 1.5 inches to 3.0 inches<lb/> Above 3.0 inches to 5.0 inches<lb/> Above 5.0 inches<lb/> 
        <bibl>Rs.103.53 + Rs.129<lb/> </bibl>
<bibl>Rs.157.78 + Rs.194<lb/> </bibl>
<bibl>Rs.208.09 + Rs.258<lb/> </bibl>
<bibl>Rs.82.44 + Rs.104<lb/> </bibl>
<bibl>Rs.646.44 + Rs.799<lb/> </bibl>
<bibl>Rs.552.12 + Rs.684<lb/> </bibl>
<bibl>Rs.322.69 + Rs.400<lb/> </bibl>
<bibl>Rs.264.47 + Rs.329<lb/> </bibl>
<bibl>Rs.223<lb/> </bibl>
<bibl>Rs.352<lb/> </bibl>
<bibl>Rs.467<lb/> </bibl>
<bibl>Rs.187<lb/> </bibl>
<bibl>Rs.1446<lb/> </bibl>
<bibl>Rs.1237<lb/> </bibl>
<bibl>Rs.723<lb/> </bibl>
<bibl>Rs.594<lb/> </bibl>
<bibl>Proceedings No.1/15(4)/2015-LS-II, dated 30.09.2015:-</bibl>
        </listBibl>
    </text>
</tei>

